{
  "$schema": "http://schema.management.azure.com/schemas/2015-01-01/deploymentParameters.json#",
  "contentVersion": "1.0.0.0",
  "parameters": {
    "adVmName": {
      "value": "ol1dc1"
    },
    "adVmSize": {
      "value": "Standard_A2_v2"
    },
    "domainName": {
      "value": "ol1smb.no"
    },
    "domainUsername": {
      "value": "ol1admin"
    },
    "domainPassword": {
        "value": "ChangeME"
    },
    "rdsVmName": {
      "value": "ol1rds"
    },
    "rdsVmSize": {
        "value": "Standard_DS2"
    },
    "rdsDnsPrefix": {
      "value": "ol1demords"
    },
    "appVmName": {
      "value": "ol1app1"
    },
    "appDnsPrefix": {
      "value": "ol1demoapppub"
    },
    "appVmSize": {
      "value": "Standard_A2_v2"
    },
    "localAdminUsername": {
      "value": "localadmin"
    },
    "localAdminPassword": {
      "value": "ChangeME"
    }
  }
}
